{
 "displayTopicName": "_Pa’al_ Active Participle for shorushim ending with ח or ע",
 "topicTokens": [
  {
   "type": "italics",
   "tokens": [
    {
     "text": "Pa’al",
     "type": "text"
    }
   ]
  },
  {
   "text": " Active Participle for shorushim ending with ח or ע",
   "type": "text"
  }
 ],
 "paragraphsBySubtopic": {
  "Pa’al Active Participle for shorushim ending with ח or ע": [
   {
    "text": "The ",
    "type": "text"
   },
   {
    "text": "_pa’al_ active participle",
    "type": "global",
    "tokens": [
     {
      "type": "italics",
      "tokens": [
       {
        "text": "pa’al",
        "type": "text"
       }
      ]
     },
     {
      "text": " active participle",
      "type": "text"
     }
    ],
    "targetSubtopic": "Pa’al Active Participle",
    "targetTopic": "Pa’al Active Participle",
    "enclosingTopic": "Pa’al Active Participle for shorushim ending with ח or ע",
    "enclosingSubtopic": "Pa’al Active Participle for shorushim ending with ח or ע"
   },
   {
    "text": " has a special conjugation for shorushim ending with “gutteral” letters like ח or ע, such as פתח, “opening.” ",
    "type": "text"
   },
   {
    "type": "table",
    "rows": [
     [
      {
       "tokens": []
      },
      {
       "tokens": [
        {
         "type": "bold",
         "tokens": [
          {
           "text": "Masculine",
           "type": "text"
          }
         ]
        }
       ]
      },
      {
       "tokens": [
        {
         "type": "bold",
         "tokens": [
          {
           "text": "Feminine",
           "type": "text"
          }
         ]
        }
       ]
      }
     ],
     [
      {
       "tokens": [
        {
         "type": "bold",
         "tokens": [
          {
           "text": "Singular",
           "type": "text"
          }
         ]
        }
       ]
      },
      {
       "tokens": [
        {
         "text": "פּוֹתֵחַ ",
         "type": "text"
        },
        {
         "type": "html_element",
         "html": "<br>"
        },
        {
         "type": "html_element",
         "html": "<br>"
        },
        {
         "text": " ",
         "type": "text"
        },
        {
         "type": "italics",
         "tokens": [
          {
           "text": "posayach",
           "type": "text"
          }
         ]
        },
        {
         "text": " ",
         "type": "text"
        },
        {
         "type": "html_element",
         "html": "<br>"
        },
        {
         "type": "html_element",
         "html": "<br>"
        },
        {
         "type": "html_element",
         "html": "<br>"
        },
        {
         "text": " [he is] opening",
         "type": "text"
        }
       ]
      },
      {
       "tokens": [
        {
         "text": "פּוֹתַחַת ",
         "type": "text"
        },
        {
         "type": "html_element",
         "html": "<br>"
        },
        {
         "type": "html_element",
         "html": "<br>"
        },
        {
         "text": " ",
         "type": "text"
        },
        {
         "type": "italics",
         "tokens": [
          {
           "text": "posachas",
           "type": "text"
          }
         ]
        },
        {
         "text": " ",
         "type": "text"
        },
        {
         "type": "html_element",
         "html": "<br>"
        },
        {
         "type": "html_element",
         "html": "<br>"
        },
        {
         "type": "html_element",
         "html": "<br>"
        },
        {
         "text": " [she is] opening",
         "type": "text"
        }
       ]
      }
     ],
     [
      {
       "tokens": [
        {
         "type": "bold",
         "tokens": [
          {
           "text": "Plural",
           "type": "text"
          }
         ]
        }
       ]
      },
      {
       "tokens": [
        {
         "text": "פּוֹתְחִים ",
         "type": "text"
        },
        {
         "type": "html_element",
         "html": "<br>"
        },
        {
         "type": "html_element",
         "html": "<br>"
        },
        {
         "text": " ",
         "type": "text"
        },
        {
         "type": "italics",
         "tokens": [
          {
           "text": "poschim",
           "type": "text"
          }
         ]
        },
        {
         "text": " ",
         "type": "text"
        },
        {
         "type": "html_element",
         "html": "<br>"
        },
        {
         "type": "html_element",
         "html": "<br>"
        },
        {
         "type": "html_element",
         "html": "<br>"
        },
        {
         "text": " [those men are] opening",
         "type": "text"
        }
       ]
      },
      {
       "tokens": [
        {
         "text": "פּוֹתְחוֹת ",
         "type": "text"
        },
        {
         "type": "html_element",
         "html": "<br>"
        },
        {
         "type": "html_element",
         "html": "<br>"
        },
        {
         "text": " ",
         "type": "text"
        },
        {
         "type": "italics",
         "tokens": [
          {
           "text": "poschos",
           "type": "text"
          }
         ]
        },
        {
         "text": " ",
         "type": "text"
        },
        {
         "type": "html_element",
         "html": "<br>"
        },
        {
         "type": "html_element",
         "html": "<br>"
        },
        {
         "type": "html_element",
         "html": "<br>"
        },
        {
         "text": " [those women are] opening",
         "type": "text"
        }
       ]
      }
     ]
    ]
   },
   {
    "text": " ",
    "type": "text"
   },
   {
    "topLevelNodes": [
     {
      "ordinal": "-",
      "ordered": false,
      "tokensOfLine": [
       {
        "text": "This conjugation exhibits a ",
        "type": "text"
       },
       {
        "text": "vowel shift for ח and ע",
        "type": "global",
        "tokens": [
         {
          "text": "vowel shift for ח and ע",
          "type": "text"
         }
        ],
        "targetSubtopic": "Vowel shift for ח and ע",
        "targetTopic": "Vowel shift for ח and ע",
        "enclosingTopic": "Pa’al Active Participle for shorushim ending with ח or ע",
        "enclosingSubtopic": "Pa’al Active Participle for shorushim ending with ח or ע"
       },
       {
        "text": ".",
        "type": "text"
       }
      ],
      "children": []
     },
     {
      "ordinal": "-",
      "ordered": false,
      "tokensOfLine": [
       {
        "text": "You can take any shoresh ending in ח or ע and replace the letters ‎פ, ‎ת, and ‎ח in the conjugations above with the three letters of your shoresh to produce the ",
        "type": "text"
       },
       {
        "type": "italics",
        "tokens": [
         {
          "text": "pa’al",
          "type": "text"
         }
        ]
       },
       {
        "text": " active participle of the given shoresh, (unless the shoresh has additional irregular features.)",
        "type": "text"
       }
      ],
      "children": []
     }
    ],
    "type": "outline"
   }
  ]
 }
}