{
 "displayTopicName": "Pi'el",
 "topicTokens": [
  {
   "text": "Pi'el",
   "type": "text"
  }
 ],
 "paragraphsBySubtopic": {
  "Pi'el": [
   {
    "text": "The \"pi'el\" (פִּעֵל), also known as the Hebrew active intensive binyan, is a ",
    "type": "text"
   },
   {
    "text": "binyan",
    "type": "global",
    "tokens": [
     {
      "text": "binyan",
      "type": "text"
     }
    ],
    "targetSubtopic": "Binyan",
    "targetTopic": "Binyan",
    "enclosingTopic": "Pi'el",
    "enclosingSubtopic": "Pi'el"
   },
   {
    "text": " that exists in Hebrew corresponding to the ",
    "type": "text"
   },
   {
    "text": "_pa'el_ in Aramaic",
    "type": "global",
    "tokens": [
     {
      "type": "italics",
      "tokens": [
       {
        "text": "pa'el",
        "type": "text"
       }
      ]
     },
     {
      "text": " in Aramaic",
      "type": "text"
     }
    ],
    "targetSubtopic": "Pa'el",
    "targetTopic": "Pa'el",
    "enclosingTopic": "Pi'el",
    "enclosingSubtopic": "Pi'el"
   },
   {
    "text": ". The ",
    "type": "text"
   },
   {
    "type": "italics",
    "tokens": [
     {
      "text": "pi'el",
      "type": "text"
     }
    ]
   },
   {
    "text": " is an ",
    "type": "text"
   },
   {
    "text": "intensive binyan",
    "type": "global",
    "tokens": [
     {
      "text": "intensive binyan",
      "type": "text"
     }
    ],
    "targetSubtopic": "Intensive",
    "targetTopic": "Intensive",
    "enclosingTopic": "Pi'el",
    "enclosingSubtopic": "Pi'el"
   },
   {
    "text": ".",
    "type": "text"
   }
  ]
 }
}